phonon_to_json/__init__.py
phonon_to_json/__main__.py
phonon_to_json/cli/__init__.py
phonon_to_json/cli/phonon_to_json_main.py
phonon_to_json/src/__about__.py
phonon_to_json/src/__init__.py
phonon_to_json/src/constants.py
phonon_to_json/src/lattice.py
phonon_to_json/src/phonon_to_json.py
phonon_to_json-0.0.3.dist-info/METADATA
phonon_to_json-0.0.3.dist-info/WHEEL
phonon_to_json-0.0.3.dist-info/entry_points.txt
phonon_to_json-0.0.3.dist-info/licenses/LICENCE
phonon_to_json-0.0.3.dist-info/RECORD
