Metadata-Version: 2.3
Name: phonon-to-json
Version: 0.0.3
Summary: Package for converting CASTEP .phonon files to .json files.
Author-email: Kit Brown <kit.daniel.brown@gmail.com>
License-File: LICENCE
Classifier: License :: OSI Approved :: MIT License
Classifier: Operating System :: OS Independent
Classifier: Programming Language :: Python :: 3
Requires-Python: >=3.8
Requires-Dist: castep-outputs
Requires-Dist: numpy
Requires-Dist: spglib
